pymoode-0.3.0.dist-info/LICENSE
pymoode-0.3.0.dist-info/METADATA
pymoode-0.3.0.dist-info/RECORD
pymoode-0.3.0.dist-info/top_level.txt
pymoode-0.3.0.dist-info/WHEEL
pymoode/__init__.py
pymoode/cython/info.cpython-311-x86_64-linux-gnu.so
pymoode/cython/mnn.cpython-311-x86_64-linux-gnu.so
pymoode/cython/spacing_neighbors.cpython-311-x86_64-linux-gnu.so
pymoode/cython/__init__.py
pymoode/cython/pruning_cd.cpython-311-x86_64-linux-gnu.so
pymoode/performance/_spacing.py
pymoode/performance/__init__.py
pymoode/misc/mnn.py
pymoode/misc/__init__.py
pymoode/misc/pruning_cd.py
pymoode/survival/replacement.py
pymoode/survival/fitness.py
pymoode/survival/__init__.py
pymoode/survival/rank_and_crowding/__init__.py
pymoode/survival/rank_and_crowding/metrics.py
pymoode/survival/rank_and_crowding/rnc.py
pymoode/operators/dem.py
pymoode/operators/variant.py
pymoode/operators/deop.py
pymoode/operators/__init__.py
pymoode/operators/des.py
pymoode/operators/dex.py
pymoode/algorithms/nsder.py
pymoode/algorithms/gde3.py
pymoode/algorithms/nsde.py
pymoode/algorithms/__init__.py
pymoode/algorithms/de.py
pymoode/algorithms/base/evolutionary.py
pymoode/algorithms/base/genetic.py
pymoode/algorithms/base/__init__.py
pymoode/algorithms/base/differential.py
