Metadata-Version: 2.1
Name: pymoode
Version: 0.3.0
Summary: A Python optimization package using Differential Evolution.
Home-page: https://github.com/mooscaliaproject/pymoode
Author: Bruno Scalia C. F. Leite
Author-email: mooscaliaproject@gmail.com
License: Apache License 2.0
Download-URL: https://github.com/mooscaliaproject/pymoode
Keywords: Differential Evolution,Multi-objective optimization,GDE3,NSDE,NSDE-R,NSGA-II,Genetic Algorithm,Crowding Distances,Evolutionary Algorithms,Evolutionary Optimization,Metaheuristics
Platform: UNKNOWN
Requires-Dist: numpy >=1.19.0
Requires-Dist: pymoo ==0.6.1
Requires-Dist: scipy >=1.7.0
Requires-Dist: future
